cli_proton_python/__init__.py
cli_proton_python/connector.py
cli_proton_python/coreclient.py
cli_proton_python/formatter.py
cli_proton_python/options.py
cli_proton_python/receiver.py
cli_proton_python/sender.py
cli_proton_python/utils.py
cli_proton_python-1.0.6.dist-info/METADATA
cli_proton_python-1.0.6.dist-info/RECORD
cli_proton_python-1.0.6.dist-info/WHEEL
cli_proton_python-1.0.6.dist-info/entry_points.txt
cli_proton_python-1.0.6.dist-info/top_level.txt
