Metadata-Version: 2.1
Name: cli-proton-python
Version: 1.0.6
Summary: AMQP 1.0 Python Proton reactive clients set(sender, receiver, connector)
Home-page: https://github.com/rh-messaging/cli-proton-python
Author: Petr Matousek
Author-email: pematous@redhat.com
License: Apache License 2.0
Keywords: unified messaging clients sender receiver amqp
Platform: UNKNOWN
Classifier: Development Status :: 5 - Production/Stable
Classifier: Intended Audience :: Developers
Classifier: Topic :: Software Development :: Quality Assurance
Classifier: License :: OSI Approved :: Apache Software License
Classifier: Programming Language :: Python :: 2
Classifier: Programming Language :: Python :: 2.7
Classifier: Programming Language :: Python :: 3
Classifier: Programming Language :: Python :: 3.3
Classifier: Programming Language :: Python :: 3.4
Classifier: Programming Language :: Python :: 3.5
Classifier: Programming Language :: Python :: 3.6
Requires-Dist: python-qpid-proton
